playwright_helper/__init__.py
playwright_helper/libs/__init__.py
playwright_helper/libs/base_po.py
playwright_helper/libs/browser_pool.py
playwright_helper/libs/executor.py
playwright_helper/middlewares/__init__.py
playwright_helper/middlewares/stealth.py
playwright_helper/utils/__init__.py
playwright_helper/utils/browser_utils.py
playwright_helper/utils/file_handle.py
playwright_helper/utils/log_utils.py
playwright_helper/utils/po_utils.py
playwright_helper/utils/template_data.py
playwright_helper/utils/type_utils.py
python_playwright_helper-0.4.3.dist-info/licenses/LICENSE
python_playwright_helper-0.4.3.dist-info/METADATA
python_playwright_helper-0.4.3.dist-info/WHEEL
python_playwright_helper-0.4.3.dist-info/top_level.txt
python_playwright_helper-0.4.3.dist-info/RECORD
