Metadata-Version: 2.4
Name: python_playwright_helper
Version: 0.4.3
Summary: playwright helper python package
Author-email: ckf10000 <ckf10000@sina.com>
License:                                  Apache License
Project-URL: Homepage, https://github.com/ckf10000/playwright-helper
Project-URL: Source, https://github.com/ckf10000/playwright-helper
Project-URL: Issues, https://github.com/ckf10000/playwright-helper/issues
Requires-Python: >=3.12
License-File: LICENSE
Requires-Dist: playwright==1.56.0; python_version >= "3.12"
Requires-Dist: playwright-stealth==2.0.0; python_version >= "3.12"
Dynamic: license-file
